{"type": "Feature", "id": 12523845, "properties": {"woe:id": 12523845, "woe:parent_id": 472902, "woe:name": "Julianehab Heliport", "woe:placetype": 14, "woe:placetype_name": "Airport", "woe:lang": "ENG", "iso:country": "GL", "meta:provider": ["geoplanet:7.3.1", "geoplanet:7.3.2", "geoplanet:7.4.0", "geoplanet:7.4.1", "geoplanet:7.5.1", "geoplanet:7.5.2", "geoplanet:7.6.0", "geoplanet:7.8.1", "geoplanet:7.9.0", "geoplanet:7.10.0", "geoplanet:8.0.0", "woeplanet:8.0.0"], "meta:indexed": "2020-08-20T21:02:12.439240", "woe:alias_ENG_V": ["JJU Airport", "JJU"], "meta:updated": "2020-08-22T01:58:35.176462", "woe:hierarchy": {"continent": 24865672, "country": 23424828, "town": 0, "planet": 1, "county": 0, "suburb": 0, "state": 20069858, "region": 0, "localadmin": 0}, "woe:timezone_id": 28350756, "woe:hash": "ffz38dbsxeux", "woe:centroid": [-46.0317, 60.748322], "geom:latitude": 60.748322, "geom:longitude": -46.0317, "geom:hash": "ffz38dbsxeux", "woe:latitude": 60.748322, "geom:centroid": [-46.0317, 60.748322], "woe:longitude": -46.0317, "woe:repo": "woeplanet-airport-gl"}, "geometry": {"coordinates": [-46.0317, 60.748322], "type": "Point"}}